jacklib/__init__.py
jacklib/api.py
jacklib/helpers.py
jacklib/version.py
pyjacklib-0.1.1.dist-info/COPYING.md
pyjacklib-0.1.1.dist-info/METADATA
pyjacklib-0.1.1.dist-info/WHEEL
pyjacklib-0.1.1.dist-info/top_level.txt
pyjacklib-0.1.1.dist-info/RECORD
