Metadata-Version: 2.1
Name: pyjacklib
Version: 0.1.1
Summary: Python bindings for libjack using ctypes.
Home-page: https://github.com/jackaudio/pyjacklib
Author: Filipe Coelho
Author-email: falktx@falktx.com
Maintainer: Christopher Arndt
Maintainer-email: chris@chrisarndt.de
License: GPLv2+
Keywords: audio,jack,midi
Platform: UNKNOWN
Classifier: Development Status :: 4 - Beta
Classifier: Environment :: MacOS X
Classifier: Environment :: Win32 (MS Windows)
Classifier: Environment :: Console
Classifier: Intended Audience :: Developers
Classifier: License :: OSI Approved :: GNU General Public License v2 or later (GPLv2+)
Classifier: Operating System :: Microsoft :: Windows
Classifier: Operating System :: POSIX
Classifier: Operating System :: MacOS :: MacOS X
Classifier: Programming Language :: Python
Classifier: Programming Language :: Python :: 3
Classifier: Programming Language :: Python :: 3.6
Classifier: Programming Language :: Python :: 3.7
Classifier: Programming Language :: Python :: 3.8
Classifier: Programming Language :: Python :: 3.9
Classifier: Programming Language :: Python :: 3.10
Classifier: Topic :: Multimedia :: Sound/Audio
Classifier: Topic :: Software Development :: Libraries :: Python Modules
License-File: COPYING.md
